kl3m_data_client/__init__.py
kl3m_data_client/client.py
kl3m_data_client/document.py
kl3m_data_client/py.typed
kl3m_data_client/cli/__init__.py
kl3m_data_client/cli/commands.py
kl3m_data_client/models/__init__.py
kl3m_data_client/models/common.py
kl3m_data_client/models/document.py
kl3m_data_client/models/stage.py
kl3m_data_client/operations/__init__.py
kl3m_data_client/operations/index.py
kl3m_data_client/utils/__init__.py
kl3m_data_client/utils/boto_types.py
kl3m_data_client/utils/console.py
kl3m_data_client/utils/parallel.py
kl3m_data_client/utils/parquet_utils.py
kl3m_data_client/utils/s3.py
kl3m_data_client-0.2.0.dist-info/licenses/LICENSE
kl3m_data_client-0.2.0.dist-info/METADATA
kl3m_data_client-0.2.0.dist-info/WHEEL
kl3m_data_client-0.2.0.dist-info/entry_points.txt
kl3m_data_client-0.2.0.dist-info/top_level.txt
kl3m_data_client-0.2.0.dist-info/RECORD
