Metadata-Version: 2.4
Name: kl3m-data-client
Version: 0.2.0
Summary: Client for interacting with KL3M data stored in S3 with JSON output support
Author: KL3M Team
License-Expression: MIT
Project-URL: Homepage, https://github.com/alea-institute/kl3m-data-client
Project-URL: Bug Tracker, https://github.com/alea-institute/kl3m-data-client/issues
Project-URL: Documentation, https://github.com/alea-institute/kl3m-data-client/tree/main/docs
Project-URL: Source, https://github.com/alea-institute/kl3m-data-client/tree/main/
Keywords: kl3m,data,s3,aws,parquet,nlp,client,tokenization
Classifier: Development Status :: 4 - Beta
Classifier: Intended Audience :: Developers
Classifier: Intended Audience :: Science/Research
Classifier: Programming Language :: Python :: 3
Classifier: Programming Language :: Python :: 3.9
Classifier: Programming Language :: Python :: 3.10
Classifier: Programming Language :: Python :: 3.11
Classifier: Programming Language :: Python :: 3.12
Classifier: Topic :: Scientific/Engineering :: Artificial Intelligence
Classifier: Topic :: Software Development :: Libraries
Classifier: Topic :: Utilities
Requires-Python: >=3.9
License-File: LICENSE
Requires-Dist: boto3>=1.26.0
Requires-Dist: pyarrow>=19.0.1
Requires-Dist: rich>=12.0.0
Requires-Dist: tokenizers>=0.21.0
Provides-Extra: dev
Requires-Dist: pytest>=7.0.0; extra == "dev"
Requires-Dist: pytest-cov>=4.0.0; extra == "dev"
Dynamic: license-file
